{
  "bytes": 454250,
  "count_of_rows": 25314,
  "description": "A variety of temporal granularities for Europe Brent and WTI (West Texas Intermediate) Spot Prices.",
  "hash": "b608511a3772e2db66596b1c7dff07dc",
  "keywords": [
    "Oil",
    "Brent",
    "WTI",
    "Oil Prices",
    "eia",
    "oil eia"
  ],
  "licenses": [
    {
      "name": "ODC-PDDL-1.0",
      "path": "http://opendatacommons.org/licenses/pddl/",
      "title": "Open Data Commons Public Domain Dedication and License v1.0"
    }
  ],
  "name": "oil-prices",
  "profile": "data-package",
  "resources": [
    {
      "bytes": 178128,
      "description": "Europe Brent crude oil spot price, daily observations, in USD per barrel (FOB). Data start: May 1987.",
      "dialect": {
        "caseSensitiveHeader": false,
        "delimiter": ",",
        "doubleQuote": true,
        "header": true,
        "lineTerminator": "\r\n",
        "quoteChar": "\"",
        "skipInitialSpace": false
      },
      "encoding": "utf-8",
      "format": "csv",
      "hash": "7bbadd514055612933ca42ddf08b11a8",
      "name": "brent-daily",
      "path": "data/brent-daily.csv",
      "profile": "tabular-data-resource",
      "schema": {
        "fields": [
          {
            "description": "Observation date in YYYY-MM-DD format.",
            "format": "%Y-%m-%d",
            "name": "Date",
            "type": "date"
          },
          {
            "decimalChar": ".",
            "description": "Spot price in US dollars per barrel (FOB).",
            "format": "default",
            "groupChar": "",
            "name": "Price",
            "type": "number"
          }
        ],
        "missingValues": [
          ""
        ]
      }
    },
    {
      "bytes": 36755,
      "description": "Europe Brent crude oil spot price, weekly averages, in USD per barrel (FOB). The Date is the Friday ending each week. Data start: May 1987.",
      "dialect": {
        "caseSensitiveHeader": false,
        "delimiter": ",",
        "doubleQuote": true,
        "header": true,
        "lineTerminator": "\r\n",
        "quoteChar": "\"",
        "skipInitialSpace": false
      },
      "encoding": "utf-8",
      "format": "csv",
      "hash": "54de0e356c39ef234cc790263f755a47",
      "name": "brent-week",
      "path": "data/brent-weekly.csv",
      "profile": "tabular-data-resource",
      "schema": {
        "fields": [
          {
            "description": "End-of-week date (Friday) in YYYY-MM-DD format.",
            "format": "%Y-%m-%d",
            "name": "Date",
            "type": "date"
          },
          {
            "decimalChar": ".",
            "description": "Spot price in US dollars per barrel (FOB).",
            "format": "default",
            "groupChar": "",
            "name": "Price",
            "type": "number"
          }
        ],
        "missingValues": [
          ""
        ]
      }
    },
    {
      "bytes": 8479,
      "description": "Europe Brent crude oil spot price, monthly averages, in USD per barrel (FOB). The Date is reported as the 15th of each month. Data start: May 1987.",
      "dialect": {
        "caseSensitiveHeader": false,
        "delimiter": ",",
        "doubleQuote": true,
        "header": true,
        "lineTerminator": "\r\n",
        "quoteChar": "\"",
        "skipInitialSpace": false
      },
      "encoding": "utf-8",
      "format": "csv",
      "hash": "84b4f5a09a792e489bccff4fe6b35f30",
      "name": "brent-month",
      "path": "data/brent-monthly.csv",
      "profile": "tabular-data-resource",
      "schema": {
        "fields": [
          {
            "description": "Reported as the 15th of the month in YYYY-MM-DD format; represents the monthly average period.",
            "format": "%Y-%m-%d",
            "name": "Date",
            "type": "date"
          },
          {
            "decimalChar": ".",
            "description": "Spot price in US dollars per barrel (FOB).",
            "format": "default",
            "groupChar": "",
            "name": "Price",
            "type": "number"
          }
        ],
        "missingValues": [
          ""
        ]
      }
    },
    {
      "bytes": 716,
      "description": "Europe Brent crude oil spot price, annual averages, in USD per barrel (FOB). The Date is reported as June 30 of each year. Data start: 1987.",
      "dialect": {
        "caseSensitiveHeader": false,
        "delimiter": ",",
        "doubleQuote": true,
        "header": true,
        "lineTerminator": "\r\n",
        "quoteChar": "\"",
        "skipInitialSpace": false
      },
      "encoding": "utf-8",
      "format": "csv",
      "hash": "3cdadc507b688ea679c38d858985ff43",
      "name": "brent-year",
      "path": "data/brent-year.csv",
      "profile": "tabular-data-resource",
      "schema": {
        "fields": [
          {
            "description": "Reported as June 30 of the year in YYYY-MM-DD format; represents the annual average period.",
            "format": "%Y-%m-%d",
            "name": "Date",
            "type": "date"
          },
          {
            "decimalChar": ".",
            "description": "Spot price in US dollars per barrel (FOB).",
            "format": "default",
            "groupChar": "",
            "name": "Price",
            "type": "number"
          }
        ],
        "missingValues": [
          ""
        ]
      }
    },
    {
      "bytes": 182779,
      "description": "WTI (West Texas Intermediate) crude oil spot price at Cushing, OK, daily observations, in USD per barrel (FOB). Data start: January 1986.",
      "dialect": {
        "caseSensitiveHeader": false,
        "delimiter": ",",
        "doubleQuote": true,
        "header": true,
        "lineTerminator": "\r\n",
        "quoteChar": "\"",
        "skipInitialSpace": false
      },
      "encoding": "utf-8",
      "format": "csv",
      "hash": "2f547ed1857d6652e548eee8c0a9d55d",
      "name": "wti-daily",
      "path": "data/wti-daily.csv",
      "profile": "tabular-data-resource",
      "schema": {
        "fields": [
          {
            "description": "Observation date in YYYY-MM-DD format.",
            "format": "%Y-%m-%d",
            "name": "Date",
            "type": "date"
          },
          {
            "decimalChar": ".",
            "description": "Spot price in US dollars per barrel (FOB).",
            "format": "default",
            "groupChar": "",
            "name": "Price",
            "type": "number"
          }
        ],
        "missingValues": [
          ""
        ]
      }
    },
    {
      "bytes": 37932,
      "description": "WTI (West Texas Intermediate) crude oil spot price at Cushing, OK, weekly averages, in USD per barrel (FOB). The Date is the Friday ending each week. Data start: January 1986.",
      "dialect": {
        "caseSensitiveHeader": false,
        "delimiter": ",",
        "doubleQuote": true,
        "header": true,
        "lineTerminator": "\r\n",
        "quoteChar": "\"",
        "skipInitialSpace": false
      },
      "encoding": "utf-8",
      "format": "csv",
      "hash": "9c0c2c389f4927e610c4905d65828234",
      "name": "wti-week",
      "path": "data/wti-weekly.csv",
      "profile": "tabular-data-resource",
      "schema": {
        "fields": [
          {
            "description": "End-of-week date (Friday) in YYYY-MM-DD format.",
            "format": "%Y-%m-%d",
            "name": "Date",
            "type": "date"
          },
          {
            "decimalChar": ".",
            "description": "Spot price in US dollars per barrel (FOB).",
            "format": "default",
            "groupChar": "",
            "name": "Price",
            "type": "number"
          }
        ],
        "missingValues": [
          ""
        ]
      }
    },
    {
      "bytes": 8733,
      "description": "WTI (West Texas Intermediate) crude oil spot price at Cushing, OK, monthly averages, in USD per barrel (FOB). The Date is reported as the 15th of each month. Data start: January 1986.",
      "dialect": {
        "caseSensitiveHeader": false,
        "delimiter": ",",
        "doubleQuote": true,
        "header": true,
        "lineTerminator": "\r\n",
        "quoteChar": "\"",
        "skipInitialSpace": false
      },
      "encoding": "utf-8",
      "format": "csv",
      "hash": "9f6bd236e47d719e68c347752d284c2a",
      "name": "wti-month",
      "path": "data/wti-monthly.csv",
      "profile": "tabular-data-resource",
      "schema": {
        "fields": [
          {
            "description": "Reported as the 15th of the month in YYYY-MM-DD format; represents the monthly average period.",
            "format": "%Y-%m-%d",
            "name": "Date",
            "type": "date"
          },
          {
            "decimalChar": ".",
            "description": "Spot price in US dollars per barrel (FOB).",
            "format": "default",
            "groupChar": "",
            "name": "Price",
            "type": "number"
          }
        ],
        "missingValues": [
          ""
        ]
      }
    },
    {
      "bytes": 728,
      "description": "WTI (West Texas Intermediate) crude oil spot price at Cushing, OK, annual averages, in USD per barrel (FOB). The Date is reported as June 30 of each year. Data start: 1986.",
      "dialect": {
        "caseSensitiveHeader": false,
        "delimiter": ",",
        "doubleQuote": true,
        "header": true,
        "lineTerminator": "\r\n",
        "quoteChar": "\"",
        "skipInitialSpace": false
      },
      "encoding": "utf-8",
      "format": "csv",
      "hash": "75305003d10c9f6d5c2834c13316633b",
      "name": "wti-year",
      "path": "data/wti-year.csv",
      "profile": "tabular-data-resource",
      "schema": {
        "fields": [
          {
            "description": "Reported as June 30 of the year in YYYY-MM-DD format; represents the annual average period.",
            "format": "%Y-%m-%d",
            "name": "Date",
            "type": "date"
          },
          {
            "decimalChar": ".",
            "description": "Spot price in US dollars per barrel (FOB).",
            "format": "default",
            "groupChar": "",
            "name": "Price",
            "type": "number"
          }
        ],
        "missingValues": [
          ""
        ]
      }
    }
  ],
  "sources": [
    {
      "name": "Daily Europe Brent Spot Price",
      "path": "https://www.eia.gov/dnav/pet/hist_xls/RBRTEd.xls",
      "title": "Daily Europe Brent Spot Price"
    },
    {
      "name": "Weekly Europe Brent Spot Price",
      "path": "https://www.eia.gov/dnav/pet/hist_xls/RBRTEw.xls",
      "title": "Weekly Europe Brent Spot Price"
    },
    {
      "name": "Monthly Europe Brent Spot Price",
      "path": "https://www.eia.gov/dnav/pet/hist_xls/RBRTEm.xls",
      "title": "Monthly Europe Brent Spot Price"
    },
    {
      "name": "Annual Europe Brent Spot Price",
      "path": "https://www.eia.gov/dnav/pet/hist_xls/RBRTEa.xls",
      "title": "Annual Europe Brent Spot Price"
    },
    {
      "name": "Daily Cushing, OK WTI Spot Price",
      "path": "http://www.eia.gov/dnav/pet/hist_xls/RWTCd.xls",
      "title": "Daily Cushing, OK WTI Spot Price"
    },
    {
      "name": "Weekly Cushing, OK WTI Spot Price",
      "path": "http://www.eia.gov/dnav/pet/hist_xls/RWTCw.xls",
      "title": "Weekly Cushing, OK WTI Spot Price"
    },
    {
      "name": "Monthly Cushing, OK WTI Spot Price",
      "path": "http://www.eia.gov/dnav/pet/hist_xls/RWTCm.xls",
      "title": "Monthly Cushing, OK WTI Spot Price"
    },
    {
      "name": "Annual Cushing, OK WTI Spot Price",
      "path": "http://www.eia.gov/dnav/pet/hist_xls/RWTCa.xls",
      "title": "Annual Cushing, OK WTI Spot Price"
    }
  ],
  "title": "Brent and WTI Spot Prices",
  "views": [
    {
      "description": "Weekly Brent crude spot price in USD per barrel. Major shocks stand out: the 1990 Gulf War spike, the 2008 financial crisis peak ($147), the 2014 OPEC supply glut collapse, the 2020 COVID demand crash, the 2022 Russia-Ukraine war surge, and the 2026 Iran war spike.",
      "name": "brent-price-history",
      "resources": [
        "brent-week"
      ],
      "spec": {
        "dateFields": [
          "Date"
        ],
        "height": 400,
        "marginLeft": 60,
        "marks": [
          {
            "staticData": [
              {
                "x": "1990-08-01"
              },
              {
                "x": "2008-07-01"
              },
              {
                "x": "2014-11-01"
              },
              {
                "x": "2020-04-01"
              },
              {
                "x": "2022-03-01"
              },
              {
                "x": "2026-02-28"
              }
            ],
            "stroke": "#e5e7eb",
            "tip": false,
            "type": "ruleX",
            "x": "x"
          },
          {
            "stroke": "#be123c",
            "strokeWidth": 1.5,
            "tip": true,
            "type": "line",
            "x": "Date",
            "y": "Price"
          },
          {
            "fill": "#6b7280",
            "fontSize": 10,
            "rotate": -45,
            "staticData": [
              {
                "label": "Gulf War",
                "x": "1990-08-01",
                "y": 130
              },
              {
                "label": "$147 peak",
                "x": "2008-07-01",
                "y": 130
              },
              {
                "label": "OPEC glut",
                "x": "2014-11-01",
                "y": 130
              },
              {
                "label": "COVID",
                "x": "2020-04-01",
                "y": 130
              },
              {
                "label": "Russia-Ukraine",
                "x": "2022-03-01",
                "y": 130
              },
              {
                "label": "Iran war",
                "x": "2026-02-28",
                "y": 130
              }
            ],
            "text": "label",
            "textAnchor": "start",
            "type": "text",
            "x": "x",
            "y": "y"
          }
        ],
        "x": {
          "label": null
        },
        "y": {
          "grid": true,
          "label": "Price (USD per barrel)",
          "tickFormat": "$,.0f"
        }
      },
      "specType": "plot",
      "title": "Brent Crude Oil Price (1987–present)"
    }
  ]
}